{
    "android_device_id": "7357b36912b9dd52",
    "android_device_model": "OnePlus8T_EEA",
    "android_device_name": "Cream",
    "app_version": "1.4.20-prod",
    "calib_version": 1,
    "data_format_version": "1.4",
    "duration": 979178000000,
    "gaze_offset": [
        0.0,
        0.0
    ],
    "glasses_serial_number": "xsl96",
    "os_version": "11",
    "pipeline_version": "1.8.0",
    "recording_id": "04860538-b0f5-4d8a-b848-7dfd42434a41",
    "scene_camera_serial_number": "luytj",
    "start_time": 1663516057870000000,
    "template_data": {
        "data": {
            "7d8bc17d-ab6b-4370-a5fa-b6b903ceba01": [
                ""
            ]
        },
        "id": "5ae3bcef-535e-47ce-a929-f59a76e86df2",
        "recording_name": "2022-09-18_11:47:37",
        "version": "2021-10-25T19:37:52.047672Z"
    },
    "wearer_id": "d83be29a-29ad-421b-bcd0-8f11f6b2b627",
    "wearer_name": "1254-P",
    "workspace_id": "6f66a25a-2ed2-4024-a250-4e89b3d668e8"
}